// 
// Decompiled by Procyon v0.5.29
// 

package com.flurry.sdk;

import java.io.ByteArrayInputStream;
import android.util.Base64;
import android.graphics.BitmapFactory;
import java.io.InputStream;
import android.graphics.Bitmap;

public class aa
{
    private static final String a;
    private boolean b;
    private Bitmap c;
    private Bitmap d;
    private Bitmap e;
    private Bitmap f;
    
    static {
        a = aa.class.getSimpleName();
    }
    
    private Bitmap a(final InputStream inputStream, final boolean b) {
        if (inputStream == null) {
            return null;
        }
        final Bitmap decodeStream = BitmapFactory.decodeStream(inputStream);
        if (decodeStream != null) {
            int density;
            if (b) {
                density = 320;
            }
            else {
                density = 160;
            }
            decodeStream.setDensity(density);
        }
        return decodeStream;
    }
    
    private Bitmap a(final String s) {
        if (s != null) {
            final byte[] decode = Base64.decode(s, 0);
            if (decode != null) {
                return this.a(new ByteArrayInputStream(decode), false);
            }
        }
        return null;
    }
    
    private void a(final InputStream inputStream, final String s) {
        if (inputStream != null) {
            if (this.g()) {
                if ("closeX_retina.png".equals(s)) {
                    this.c = this.a(inputStream, true);
                    return;
                }
                if ("pause_button_retina.png".equals(s)) {
                    this.d = this.a(inputStream, true);
                    return;
                }
                if ("play_button_retina.png".equals(s)) {
                    this.e = this.a(inputStream, true);
                    return;
                }
                if ("more_info_retina.png".equals(s)) {
                    this.f = this.a(inputStream, true);
                }
            }
            else {
                if ("closeX.png".equals(s)) {
                    this.c = this.a(inputStream, false);
                    return;
                }
                if ("pause_button.png".equals(s)) {
                    this.d = this.a(inputStream, false);
                    return;
                }
                if ("play_button.png".equals(s)) {
                    this.e = this.a(inputStream, false);
                    return;
                }
                if ("more_info.png".equals(s)) {
                    this.f = this.a(inputStream, false);
                }
            }
        }
    }
    
    private boolean g() {
        return fc.d() >= 1.5f;
    }
    
    public boolean a() {
        return this.c != null && this.d != null && this.e != null && this.f != null;
    }
    
    public Bitmap b() {
        return this.c;
    }
    
    public Bitmap c() {
        return this.d;
    }
    
    public Bitmap d() {
        return this.e;
    }
    
    public Bitmap e() {
        return this.f;
    }
    
    public void f() {
        // 
        // This method could not be decompiled.
        // 
        // Original Bytecode:
        // 
        //     0: aconst_null    
        //     1: astore_1       
        //     2: aload_0        
        //     3: getfield        com/flurry/sdk/aa.b:Z
        //     6: ifeq            10
        //     9: return         
        //    10: invokestatic    com/flurry/android/impl/ads/FlurryAdModule.getInstance:()Lcom/flurry/android/impl/ads/FlurryAdModule;
        //    13: invokevirtual   com/flurry/android/impl/ads/FlurryAdModule.e:()Lcom/flurry/sdk/t;
        //    16: invokevirtual   com/flurry/sdk/t.c:()Ljava/io/File;
        //    19: astore_2       
        //    20: aload_2        
        //    21: ifnull          128
        //    24: new             Ljava/io/BufferedInputStream;
        //    27: dup            
        //    28: new             Ljava/io/FileInputStream;
        //    31: dup            
        //    32: aload_2        
        //    33: invokespecial   java/io/FileInputStream.<init>:(Ljava/io/File;)V
        //    36: invokespecial   java/io/BufferedInputStream.<init>:(Ljava/io/InputStream;)V
        //    39: astore_3       
        //    40: new             Ljava/util/zip/ZipInputStream;
        //    43: dup            
        //    44: new             Ljava/io/BufferedInputStream;
        //    47: dup            
        //    48: aload_3        
        //    49: invokespecial   java/io/BufferedInputStream.<init>:(Ljava/io/InputStream;)V
        //    52: invokespecial   java/util/zip/ZipInputStream.<init>:(Ljava/io/InputStream;)V
        //    55: astore          4
        //    57: aload           4
        //    59: invokevirtual   java/util/zip/ZipInputStream.getNextEntry:()Ljava/util/zip/ZipEntry;
        //    62: astore          12
        //    64: aload           12
        //    66: ifnull          238
        //    69: aload_0        
        //    70: aload           4
        //    72: aload           12
        //    74: invokevirtual   java/util/zip/ZipEntry.getName:()Ljava/lang/String;
        //    77: invokespecial   com/flurry/sdk/aa.a:(Ljava/io/InputStream;Ljava/lang/String;)V
        //    80: goto            57
        //    83: astore          9
        //    85: aload_3        
        //    86: astore          10
        //    88: iconst_3       
        //    89: getstatic       com/flurry/sdk/aa.a:Ljava/lang/String;
        //    92: ldc             "Media player asset file not found!!!"
        //    94: invokestatic    com/flurry/sdk/eo.a:(ILjava/lang/String;Ljava/lang/String;)V
        //    97: aload           4
        //    99: invokestatic    com/flurry/sdk/fe.a:(Ljava/io/Closeable;)V
        //   102: aload           10
        //   104: invokestatic    com/flurry/sdk/fe.a:(Ljava/io/Closeable;)V
        //   107: aload_0        
        //   108: invokevirtual   com/flurry/sdk/aa.a:()Z
        //   111: ifne            128
        //   114: iconst_3       
        //   115: getstatic       com/flurry/sdk/aa.a:Ljava/lang/String;
        //   118: ldc             "Media player assets incomplete, deleting assets file"
        //   120: invokestatic    com/flurry/sdk/eo.a:(ILjava/lang/String;Ljava/lang/String;)V
        //   123: aload_2        
        //   124: invokevirtual   java/io/File.delete:()Z
        //   127: pop            
        //   128: aload_0        
        //   129: getfield        com/flurry/sdk/aa.c:Landroid/graphics/Bitmap;
        //   132: ifnonnull       154
        //   135: iconst_3       
        //   136: getstatic       com/flurry/sdk/aa.a:Ljava/lang/String;
        //   139: ldc             "Missing close button, loading default"
        //   141: invokestatic    com/flurry/sdk/eo.a:(ILjava/lang/String;Ljava/lang/String;)V
        //   144: aload_0        
        //   145: aload_0        
        //   146: ldc             "iVBORw0KGgoAAAANSUhEUgAAABkAAAAZCAYAAADE6YVjAAAAGXRFWHRTb2Z0d2FyZQBBZG9iZSBJbWFnZVJlYWR5ccllPAAAA2hpVFh0WE1MOmNvbS5hZG9iZS54bXAAAAAAADw/eHBhY2tldCBiZWdpbj0i77u/IiBpZD0iVzVNME1wQ2VoaUh6cmVTek5UY3prYzlkIj8+IDx4OnhtcG1ldGEgeG1sbnM6eD0iYWRvYmU6bnM6bWV0YS8iIHg6eG1wdGs9IkFkb2JlIFhNUCBDb3JlIDUuMy1jMDExIDY2LjE0NTY2MSwgMjAxMi8wMi8wNi0xNDo1NjoyNyAgICAgICAgIj4gPHJkZjpSREYgeG1sbnM6cmRmPSJodHRwOi8vd3d3LnczLm9yZy8xOTk5LzAyLzIyLXJkZi1zeW50YXgtbnMjIj4gPHJkZjpEZXNjcmlwdGlvbiByZGY6YWJvdXQ9IiIgeG1sbnM6eG1wTU09Imh0dHA6Ly9ucy5hZG9iZS5jb20veGFwLzEuMC9tbS8iIHhtbG5zOnN0UmVmPSJodHRwOi8vbnMuYWRvYmUuY29tL3hhcC8xLjAvc1R5cGUvUmVzb3VyY2VSZWYjIiB4bWxuczp4bXA9Imh0dHA6Ly9ucy5hZG9iZS5jb20veGFwLzEuMC8iIHhtcE1NOk9yaWdpbmFsRG9jdW1lbnRJRD0ieG1wLmRpZDpGQTdGMTE3NDA3MjA2ODExODIyQUY3MzAxRkZEQzQ0RiIgeG1wTU06RG9jdW1lbnRJRD0ieG1wLmRpZDozQjgwQTA0RTdENjgxMUUzOEFDQ0U3MEVEOUU1NzA1NiIgeG1wTU06SW5zdGFuY2VJRD0ieG1wLmlpZDozQjgwQTA0RDdENjgxMUUzOEFDQ0U3MEVEOUU1NzA1NiIgeG1wOkNyZWF0b3JUb29sPSJBZG9iZSBQaG90b3Nob3AgQ1M2IChNYWNpbnRvc2gpIj4gPHhtcE1NOkRlcml2ZWRGcm9tIHN0UmVmOmluc3RhbmNlSUQ9InhtcC5paWQ6MDI4MDExNzQwNzIwNjgxMTgwODNERDQ2MEY4MkUxRTYiIHN0UmVmOmRvY3VtZW50SUQ9InhtcC5kaWQ6RkE3RjExNzQwNzIwNjgxMTgyMkFGNzMwMUZGREM0NEYiLz4gPC9yZGY6RGVzY3JpcHRpb24+IDwvcmRmOlJERj4gPC94OnhtcG1ldGE+IDw/eHBhY2tldCBlbmQ9InIiPz5pVsUjAAADDklEQVR42rxWX0hTcRTWKLQXp0FMM/XJJYrD0O1ubCJ7CFY5qQfdi75Evg1DZI/GwqfwwQf/IGJP6oNDKKhGQ6SNbc5Ng3AIMp9EU4eCKVSaEX0f3Bs3c/deEzrwcX/33nO/b+fsnPP75e7s7OQoWB7gAB4AVqAC0AEHwDoQB14B7/V6/XE2ktwsIpeBR4AvnU5/iUajq+FweHN5efnz9vb2cUlJSZ7RaCxsamq6abfbqwwGQwF8nwNDEPuuReQW4J+fnz8ZHx9fCgQCiqHSrFbrta6uLrPD4biKWzeEVpVETMC7qampZE9PTyLnnNbf3y90dHQIWN6F0O/vL8l8qoDZ0dHRyL8I0Lxeb2JkZCSMZTCTyVSdjuQKsDQxMbFFx5wLmhhRKZb1iOhEiuRJKBT6JhcYHh62t7e3V2ghpR/95RGB7yt5pXTl8/nAwMAfEcTj8Y2+vr42NSG+px/95c9FPi/Sls9SbU6lUnuJRGJf7jQ5Ock+8JOAV/H+TIHe3t6/3pMPJb+HUndR5H4kElk761cqCSkJSIb+WoPIPaarfmFhYStbOkhAInnqtAjQ0GvkbWAk5UjXgVLe5RGZzeaYy+WyqQnQVlZWyFtGER1HhVoFkdBkMsXcbved6enpWTUBmsirY7oOi4uL87SUaUtLi83v98/yqqW8Rd5DRrJRU1NTgKbcVStTKUXJZPKTUtVJVl1dzcG5SZFFm81WOjc3t6tFQGt50zCh2fVJigRw48P143n6QIsQeCu5XVDkNWp5SBCEInlDailTJSEUSSF4r5Off/wRZ1p3d7dwao8o01KmUh/RX/4ck9xCXgzIo/86hU+4o+GF1efz3b6IAL6vIw+WbRQ4a2dsAN7OzMykPB5P9LwCg4ODttbWViOHLgQWlfb4cuBlLBb7OTY2thQMBjNq5E6nU9/Z2WlCKzAzDyGwrvW08hh4irm2zynNIYrRfQD/Y3YyKkdnsVhuNDY2VtbW1hbB9xnwAgI/tB6JJOOG1sztgH+ieO5iFx+K564PTC/whlWUjeSXAAMAkm7GSBHyFdsAAAAASUVORK5CYII=\n"
        //   148: invokespecial   com/flurry/sdk/aa.a:(Ljava/lang/String;)Landroid/graphics/Bitmap;
        //   151: putfield        com/flurry/sdk/aa.c:Landroid/graphics/Bitmap;
        //   154: aload_0        
        //   155: getfield        com/flurry/sdk/aa.d:Landroid/graphics/Bitmap;
        //   158: ifnonnull       180
        //   161: iconst_3       
        //   162: getstatic       com/flurry/sdk/aa.a:Ljava/lang/String;
        //   165: ldc             "Missing pause button, loading default"
        //   167: invokestatic    com/flurry/sdk/eo.a:(ILjava/lang/String;Ljava/lang/String;)V
        //   170: aload_0        
        //   171: aload_0        
        //   172: ldc             "iVBORw0KGgoAAAANSUhEUgAAAGUAAABmCAYAAADS6F9hAAAAGXRFWHRTb2Z0d2FyZQBBZG9iZSBJbWFnZVJlYWR5ccllPAAAA2hpVFh0WE1MOmNvbS5hZG9iZS54bXAAAAAAADw/eHBhY2tldCBiZWdpbj0i77u/IiBpZD0iVzVNME1wQ2VoaUh6cmVTek5UY3prYzlkIj8+IDx4OnhtcG1ldGEgeG1sbnM6eD0iYWRvYmU6bnM6bWV0YS8iIHg6eG1wdGs9IkFkb2JlIFhNUCBDb3JlIDUuMy1jMDExIDY2LjE0NTY2MSwgMjAxMi8wMi8wNi0xNDo1NjoyNyAgICAgICAgIj4gPHJkZjpSREYgeG1sbnM6cmRmPSJodHRwOi8vd3d3LnczLm9yZy8xOTk5LzAyLzIyLXJkZi1zeW50YXgtbnMjIj4gPHJkZjpEZXNjcmlwdGlvbiByZGY6YWJvdXQ9IiIgeG1sbnM6eG1wTU09Imh0dHA6Ly9ucy5hZG9iZS5jb20veGFwLzEuMC9tbS8iIHhtbG5zOnN0UmVmPSJodHRwOi8vbnMuYWRvYmUuY29tL3hhcC8xLjAvc1R5cGUvUmVzb3VyY2VSZWYjIiB4bWxuczp4bXA9Imh0dHA6Ly9ucy5hZG9iZS5jb20veGFwLzEuMC8iIHhtcE1NOk9yaWdpbmFsRG9jdW1lbnRJRD0ieG1wLmRpZDowNzgwMTE3NDA3MjA2ODExODIyQUZCNjBENDUyODE3NiIgeG1wTU06RG9jdW1lbnRJRD0ieG1wLmRpZDo1MUQwMjYzNDM5QjIxMUUzQTAxNzhFNEMxQzM2NjE2MSIgeG1wTU06SW5zdGFuY2VJRD0ieG1wLmlpZDo1MUQwMjYzMzM5QjIxMUUzQTAxNzhFNEMxQzM2NjE2MSIgeG1wOkNyZWF0b3JUb29sPSJBZG9iZSBQaG90b3Nob3AgQ1M2IChNYWNpbnRvc2gpIj4gPHhtcE1NOkRlcml2ZWRGcm9tIHN0UmVmOmluc3RhbmNlSUQ9InhtcC5paWQ6N0JCQUQzMjkwOTIwNjgxMTgwODNFMjBCMTVERDZERDEiIHN0UmVmOmRvY3VtZW50SUQ9InhtcC5kaWQ6MDc4MDExNzQwNzIwNjgxMTgyMkFGQjYwRDQ1MjgxNzYiLz4gPC9yZGY6RGVzY3JpcHRpb24+IDwvcmRmOlJERj4gPC94OnhtcG1ldGE+IDw/eHBhY2tldCBlbmQ9InIiPz7H1SsRAAASbklEQVR42uxdCVAUVxoeBrnZZBEIKiggh4iAkmDAQCLK6nriFTdScWWzWouplJuKMbFiopbZXVOWxiSS1JItjYmbVVkFIYIxGgMqKF6LREBUFAiHgIPIfSmz/zfpsUaZed09tMwA81f91RTzpvu973v/9fp1zxCZkYtSqbSnwzjSIFIfUg9Sd1JH0qGkDlq+Vk96l7SOtIy0lPQG6c+kBWZmZs3GPGYzIyQBIE8jjSSNIA2QuJ9K0nzSLNJM0uNEUr2JlJ5EjKDDItLFpOGk8j68fDdpNukB0iQiqEo2WIWIsCBdRHqEtFtpHNLN9Qf9shhMZDxNuoa0XGncUs718+mBTIY96fuk95T9S+5x/bYfSGTISeNIa5X9W2q5ccj7OyETSS/3BWKtra0dfUROLsbV77Iv6rQ1HTaTvilFJtXS0tJ+8+bNWtK6oqKi+hs3bjQUFxe3VFRUtJeVlbV3d3cjzX1Aai6Xy83c3d2t3dzcrL29ve18fHye9vPzc/Dy8nIkfcbOzs5aooztM9J1lK21Gz0pREgQ6T7qrL++5+jq6rp/5cqV8oyMjLLvvvuuIisrS0HAt9JHbaQdpJ2c3ufIeFzMSYeQWnJqRWpDhNlGREQ4RUdHu02ZMsU9MDBwpIWFxZBejLWQxhlD+rPRkkKdfI0O/+RAEPtdZW5ubllycnLRl19+WaJQKFCNN8JQSKWcjbAUO9KnnJycHOPi4jwXLlzoFxwc7E7g6oMHJsnr9NXdRkUK4YnZtgOdE/tdxILDhw9f+eijj67k5eVV0r/ukTZwLuJJC1wrUt7fjh8/3vW9994LnDt3bqCtra2VHufCZPwrkXPf4KQQIU+RHqDOTBcbJ/bt2/e/devW5d65c+c2t07VacC8BG7O0dnZefjmzZuDY2JinhUbfwiHY4TDYtJGg5FCnXDmOjJB6Hfu37/ffejQocurVq06W1NTA8u400dWIcZ6nF1cXFzj4+MnLViwYMKQIUPkIjC5jAlKeqfPSaGLu5EepYuPE/odypwqVqxY8VN2djZWbKuNjAxt5AwLDw/32blz51TK4NxEYIOV6BmkFX1GCiyEsqFMymYEZVjIpj777LOstWvX5tD3fuGCY38RKxrnqC1btoS9+eabEUKzNRpnIX0vUh+LMdODkKfogqfoguOFtK+srLy7dOnSI5mZmT9zcaO/imNkZGTQt99+O8vV1XWoQGLyCKeXxMYYM5GEDCFNFxrUz549Wzxv3rw0CuQ3JE5rDSXWlAj4pKamzpk0aZK3iOA/W0xWJqraJubjhRKSmJh4iQq1/URIwQAhBNKO8WBcGJ+gWU94ATexwUxwYUimuFJI208//fTkkiVLDlFnSow8mOu1xIJxYXwYpyCQCTeusJbOfXFLJxeIdUu+th9//HHmmjVrvqc/FbKBL07btm2b+fbbb0cKwLCT8JsoZElGLuBk1lRbJAohBDOHCDkySAiBKDBeIRYD/IAjt1jbO1LIVD+i4slPSAx56623jvTzDEsfqcO4hcQY4Ag8e+W+uPsGOXzkIcui4PcNXXDQbjqguDEiKysrVkBWhhgbRpZzQbSl4A4bFX1f8RGCOmT+/PlJg5kQzqNUAQfgwccfcGXdwZQzLvIXql4D+Cr12NjYlNra2mKZSWTAAXgAF1Y74Ap8RZHCbXL4B18nduzYcfrEiROXBmDaq7fBAA/gIiCB+oeuzRhaY0pHR8cGS0vLTayTYnFx3Lhx8cS4wsRFj/jiVFBQsIpvEbOzs3OjlZXVh7yWgn1O5ubm77BOhuX3uLi4dBMhOl2/AvgAJ1Y74KxtX5lcC3srqTFzj1NKSkruqVOn8kzw6xbgA5x4SLEH3kz3ha2aFKTKKRC56DoR7hj6+vpuraqqKpVyEMuXL3cncx8qtP3t27ebt2/ffkPX56tXr/YZPny44A105I7v7tq1q0zKMY0YMcLj+vXr77DuYBLeNYT3SEqRu7SSQub2MrF3gHUh6nj2ihUrvpY6uF+8ePEvwcHBoWT6/GtDZmayioqKYg8PD52FWGlp6Xtubm7eNNGExABZbm7uuZCQkH9JHV527tz5J5pw4axGDx48WEyF5cGHRabmh21tbW/Y2+ueXNjk8MEHHxx/EtkWJRfWZMpwn7xtaQBob8lzPktSTDTe81FSo7r+kwgvwCsmJiaEtRkDuNPhYI+YgscRiJDJrCukpaXlVVdXV5oihnABXsCN1Qa4c4+DPEpKU1NTDGvZBfuytm3bdtJUk4i3FuCmZPtRMw7/R0nBTj/WmbFR7sKFC7dMGIsX4Ab8eOLko6TgkTbKEJ7lcV1I7zpNEOslnRx+OgX4c48W/kpKY2PjLNaWTazlJCQkXDBhq78AP9aaGPAHDw9JaW9vn8k6ITZbU11wxwSt/gL8gCOrjZoHFSmUroWyGp85c+aaKcD3PuBzOOoUNQ94yooyMnsvVuMjR44UmDDtvfDhCB7Ah7y+vn48KxXGssoPP/xgyrokEOAIPFlJGPiQNzc3M11XSUlJTXd3d7sJUgn8F+EIPFltwAdiij8PKdUmOKUTAXj6yy0sLDxMpBgPKeBDbmVl5crnvkxQSkoKE0/wAUv5LatRcXGx0dUnWGo35vP1Bk/wIbe0tPwND7MNxkYKltqlEixkEBB9aSkNPGP7DUixYzW6evVqg7ERIuXMJnch0++hYP2ED0/wIWTb6n1jIQRkAESpxNzcXFKrE5gW8+LJJKWtrc2oVoVtbGwkm9U4D85nCOHDVc4DgqUxEYKZLeX5+jLAi8FVLsBlGPzteXBZUgZjEIL7/AZywbx4yjs6OlpZDQICAuwMbSFSxRG4LFtb2z7NtsTiCT5AShOr0ejRow3yZji4KuyskQpAWIadnZ3BLEQonuBjCEeKzs13vr6+TnTosx0sAA0ZkRTgqWsQnE/KeNQb4fBkkiJvamqq4WH2mb7qsLW1tcq9SDWb4fqkThAksBQmnuADS/fMV1V4enqOkJlEMuHDE3zgJhfzBpa7u7uJFAmFD0/wIS8vL7/MajRy5EhXY0iLB4IAR+DJagM+5CdOnDgv+/VV41qFfLzNggULhpkg7b0AR+DJaKIEH/Kvv/66UqFQMLOr6OjoQBOkvRc+HMED+EBF31VVVZXPajxx4kQTKRIIH44cD12qZZbS0tJsVmNvb29f8oVWJlj1F+AHHFlt1DyoSElMTExj7QrHi8fefffdCSZo9Rfgx3qBG/AHDw9J2bt371UyHdWjarqepIqKioowQau/8OEH/MHDQ1JQ3V+5ciVDg7UeX/Lz8xs7efLkoSZ4xQtwA36sNhz+HZqkyFJTU/eDD9xjePCg50uxsSv8/fffjzJBLF6AG8+LqJUc/rJHSElISDh/69atfF2WAnnxxRcnmwK++AAP3FhtgDvw70EKSWt2dnYq/sACnrYHOK2trW0+//zz35mgFi7AC7ix2nC4P7yv9YhJeXl5eV++fPm8vb29A56s1XZzqa2trdXf3/8dSt8k3V/88ssvh/ItQWhKXV1d/Z49ezJ0fb5s2bIpjo6ODkLPV15eXnnw4MFzUo7Jw8PDurCwcKuNjY2trjbNzc31EyZMeP7mzZvFWkmB5aSlpe2ZPXv2q11dXar7EdqW0TMyMn6YOnXqfyWeVJhNYvYEwJRbGJ/jDp+YewDYzNAm5YB++umnP0yZMuX3rDbp6en/mTNnzjKZxvM/j9+j7/7kk0++6OzsbMPNIV3PtL/00ku/i46OdpGYFADSIEJbeM7XIvJ8khICfIATcxYQzsBb9tgDWT02TuDVSMRwOlc0aiWGYo55fHz8n0yrx9oFuAAfcx1319S1IHDmXs0lY5ICAjds2PBJe3t7E0iBG9OWjY0aNcqXfPpkEwU9BbgAHxYhwBc4y7Q8ca11i9EFkpSUFNU7WnB/m06g9eKvvPLKksWLF5tugmkI8AAuuj5HDYhaEPgCZ21tdLofysD8KX8+6uzsPLK1tVXlyrTtLMFvnzz33HN/o+ylY7ATgprk0qVL6/EbLNo+h9dB4qRQKMpHjx49gzKvQq3uj5GqXd26desOLJRhQwOsRZsbQwe+//775YM9vmD8wEEXIRprikrgCnx1nYsPSOdTp059SxXpdPUbgbB3Skf6dyQqKippsJJCAXsRlQmztK6h0GQGfpjcp0+fPkZZ2VLZrz/mIxNlKWrvFBsb+3cq1KrUhaSu+IIO7d+/f+pgJATj1kWIGjPEZuAIPFmEqLJbvgveu3evsrGx8cHMmTOjKKbIcQEUldqyvYCAgKAxY8Y0JiUllQ4WQvbu3Ru5ZMmSpbo+h4UAK/xUx5o1azb9+OOPeK+Xslek4AQXL1687unp+UxwcPCzyBxADC6kbdd6YGDg+LFjxzYfPHiwZDBYCIsQBHZkW/AylCbvXr9+/TbNNS59Y4qm+Obk5HwZGhoaCVJQVLJ2MyLGTJs2LZn7tdIBF9SPHz++kOWyEH9hJYjB586dywwLC4ujf18Xcn5RGZODg8OLZDX/pHRuHNJkzAIQo2tbaGFh4cUZM2Z8NZDSZaS9R48e/bO/v38IixBMXBBSUlJSEBIS8np9ff1pwaSL6RCdOHvevHnra2trf1E/dNPS0qLzPY3oeG5u7gcDpcDEODAeFiFwWW1tbarJSjXcL8ALuIm5jj61hcWkSZNiDh8+vHno0KGuaosBSboeWyDSuhITE/cvW7bsZH90Z3BXWDpBpU7uWuezGXDpapdFRFTOnTt33dmzZ/eBKzHX02c7endFRcW1vLy8+lmzZj37FAlIUS9caosxNCjzoKCg8cuXL/e9SXLt2rWW/kIIVnspfrweERERhXGw0l51nEXG+uqrr27KzMzcJ9PjbYK9qcLtKHgtTk1N3URV7CiYLNwYSGE9MEoEPqAC6vhrr712WOobZVIKblDt3r17LhXO08wZz1KgMMTYUbGDEIVCAZe1kZIirB3qNfl6uzRi7efntzA9PX0dgj86B5+KWMP3XAjNrBaagUffeOONE8aUCCCQf/HFF1GUOc6gCpz5KBwmIcasfmyPJlnB7NmzNxcVFSXLevGLfVKsV1mQB5t27Nixd5Auw4TVVT+qWCwtsATP+GVnZ2d8+OGHmSdPnrxrKDKwDWjDhg2R4eHhU6iusGUWbtyyCcaKOIoxnj9/PnP69OlbqdA+LjaGPAlS1Flc2K5du1bExsb+ET/SiRmEzguxGm6gylu3bv1M6WbOli1b8vrCemAVa9euHU9pexhZepCQ36NXp7twVyCDxnX/m2+++TfFy52yX38qq9evdZR6ZdeXMqxXtm/fvpIysxHqOKMyJ5pRqGyFPLuObK2srKyAZl9+UlJS0aFDh6qlyNqQReFxhEWLFvk9//zzAe7u7uNY2dQj2Q2RADIwHvVEo4BetXr16gTKzBKFFoaGIAUy1MXFZdqBAwf+TBnLNBqEmeayP1ya2PerIP5UV1eXkvVUUPJWjTcBXb16tZ6Ozfn5+S2ahAF4PBbt7e1tP3bsWAc6Ont5eQ0jq3AbNmyYB1+c0EYGXBVipbr/NLmUWVlZx6lu+aqmpgbuymBuV2yqHRoXF/c3FJoAjaxG2dDQ8FCpvlFSIqaUShCblBIKTSZVH9X9pSJZ1V+MB+PC+PQsKQwuzjSzFpB57yFSGjEozYFCm5ublRQwlSDO0II+ELmqPmn2j6wEk6oR48B4MK7+vjoBF+lH/nt5WlpaMma0NnIoa1H9r68JwrVwTVwbfXicDPQX/Ub/MY4n5PINJgioE3x8fOKSk5P/29TUdBfkULxQ0t+PEKQGBZ8BGClJwrm4mf+IRWi6Vbgu9A/9RH/Rb67/fTaL+1qwC3IM1TZBGzduDJ8/f34EpaMBSAgQTJHdaNsLoL6xhiOSBKg6g8URqv6e5hGBGkcsBan/flywCoHskI7KkpKS/JSUlKxNmzZlk+Xgx5evyfr4hxcMaYpIv0aBoBdeeCFg1apVz1G2FuLq6upN4JmBHAAJFfITTiJTYxURUPpbWVVVVUzZ1MX4+PhLZ86cyeeI+EVmoFfJG4t/RAXtQerp5+fnuXLlyoCwsLAx2HDu5OTkCpLUM12tIEqt2qxKDb6mZXF3S5V1dXWV2FCdk5NzLSEhIb+oqAh3SaGlMgF3BgcLKZqCHRq4/4KtOi5UXwyfM2eOa2hoqJuHh8czJE4ODg6OVLzZo+ZQL4mAHDUZCM6obShuNNfX19dRGqsoLS2tPXfuXAUF7Uqqd25TM7yTBkf85rFR3YTrD5kEAixe04tH+/BaJntOrTS0x5KahjZz2sAVefd6uzb1pOX/AgwAk7JbbtKygVIAAAAASUVORK5CYII=\n"
        //   174: invokespecial   com/flurry/sdk/aa.a:(Ljava/lang/String;)Landroid/graphics/Bitmap;
        //   177: putfield        com/flurry/sdk/aa.d:Landroid/graphics/Bitmap;
        //   180: aload_0        
        //   181: getfield        com/flurry/sdk/aa.e:Landroid/graphics/Bitmap;
        //   184: ifnonnull       206
        //   187: iconst_3       
        //   188: getstatic       com/flurry/sdk/aa.a:Ljava/lang/String;
        //   191: ldc             "Missing play button, loading default"
        //   193: invokestatic    com/flurry/sdk/eo.a:(ILjava/lang/String;Ljava/lang/String;)V
        //   196: aload_0        
        //   197: aload_0        
        //   198: ldc             "iVBORw0KGgoAAAANSUhEUgAAAGUAAABmCAYAAADS6F9hAAAAGXRFWHRTb2Z0d2FyZQBBZG9iZSBJbWFnZVJlYWR5ccllPAAAA2hpVFh0WE1MOmNvbS5hZG9iZS54bXAAAAAAADw/eHBhY2tldCBiZWdpbj0i77u/IiBpZD0iVzVNME1wQ2VoaUh6cmVTek5UY3prYzlkIj8+IDx4OnhtcG1ldGEgeG1sbnM6eD0iYWRvYmU6bnM6bWV0YS8iIHg6eG1wdGs9IkFkb2JlIFhNUCBDb3JlIDUuMy1jMDExIDY2LjE0NTY2MSwgMjAxMi8wMi8wNi0xNDo1NjoyNyAgICAgICAgIj4gPHJkZjpSREYgeG1sbnM6cmRmPSJodHRwOi8vd3d3LnczLm9yZy8xOTk5LzAyLzIyLXJkZi1zeW50YXgtbnMjIj4gPHJkZjpEZXNjcmlwdGlvbiByZGY6YWJvdXQ9IiIgeG1sbnM6eG1wTU09Imh0dHA6Ly9ucy5hZG9iZS5jb20veGFwLzEuMC9tbS8iIHhtbG5zOnN0UmVmPSJodHRwOi8vbnMuYWRvYmUuY29tL3hhcC8xLjAvc1R5cGUvUmVzb3VyY2VSZWYjIiB4bWxuczp4bXA9Imh0dHA6Ly9ucy5hZG9iZS5jb20veGFwLzEuMC8iIHhtcE1NOk9yaWdpbmFsRG9jdW1lbnRJRD0ieG1wLmRpZDowNzgwMTE3NDA3MjA2ODExODIyQUZCNjBENDUyODE3NiIgeG1wTU06RG9jdW1lbnRJRD0ieG1wLmRpZDo1MUQwMjYzODM5QjIxMUUzQTAxNzhFNEMxQzM2NjE2MSIgeG1wTU06SW5zdGFuY2VJRD0ieG1wLmlpZDo1MUQwMjYzNzM5QjIxMUUzQTAxNzhFNEMxQzM2NjE2MSIgeG1wOkNyZWF0b3JUb29sPSJBZG9iZSBQaG90b3Nob3AgQ1M2IChNYWNpbnRvc2gpIj4gPHhtcE1NOkRlcml2ZWRGcm9tIHN0UmVmOmluc3RhbmNlSUQ9InhtcC5paWQ6N0JCQUQzMjkwOTIwNjgxMTgwODNFMjBCMTVERDZERDEiIHN0UmVmOmRvY3VtZW50SUQ9InhtcC5kaWQ6MDc4MDExNzQwNzIwNjgxMTgyMkFGQjYwRDQ1MjgxNzYiLz4gPC9yZGY6RGVzY3JpcHRpb24+IDwvcmRmOlJERj4gPC94OnhtcG1ldGE+IDw/eHBhY2tldCBlbmQ9InIiPz600gV7AAAUiklEQVR42uxdCVBU17ZtGpDR+BAIPFFBGSQyCI4oGIkEozihRtGKSvI1HxPjVxPUCon69UUtS6OJxHoklTi9lICKwkfUKEYIoCj6ABEEBAEZZBRkFpH+e7X3+lrtvt2N0AOwq3a6I7f7nrPW2dMZbmvwVFwEAoEhvTiQOpPaklqRWpIakw4kNRLzsVrSR6Q1pEWkhaT3SG+TZmpoaDSqcp81VJAEgOxN6knqTurUxe0UkGaQJpHGkV4ikmr7SHmdiEH0soB0IUMEX4G372AIOkkaQQSV8XqrEBHapAtIz5F2CFRDOpj2oF3avYmMAaSBpMUC1ZZipp0DejIZhqTfkNYJ1EvqmHYb9iQy+KQBpJUC9ZZKph98dSdkHGmqIhBrbm5+oiBy0J9xapd9UaN16WUn6dquyKSamppa8/PzK0lrsrOza+/du/c4Ly+vqaSkpLWoqKi1o6MDae4zUk0+n69haWmpO3jwYF0bGxsDW1vbAfb29kbW1tbGpG8bGBjodlHG9iNpEGVrrSpPChHiTBpKjR3Z2e94+vRpe0ZGRnF8fHxRZGRkSWJiYjUB30x/aiF9QtrGaDtDxquiSapF2o9RHVI9Ikzfw8PDxNfXd/CUKVMsnZychmhra2u9QV+zqJ9LSG+rLCnUyE/o5Z8MCPJ+VpCamlp0+vTp7J9//rmguroa1XgDKarvrhyNsBQE7f4mJibGAQEBw+bPn2/v6upqSeB2Bg8Mks/oo4dVihTCE6PtABon72cRC6KjozN27dqVkZ6eXkr/VEf6mHER3S1wrUh5/zZq1CiLr7/+2mn27NlO+vr6Op34LgzG/yFy2pVOChHyFulJasw0eeNEaGjov4OCglKrqqoeMvNUbUrMS+DmjE1NTf++c+dO1yVLloyWN/4QDhcJh4Wk9UojhRphyjTERdbPtLe3d5w5cyZtzZo11yoqKmAZVQqyCnmsx9TMzMwiODh44rx581y0tLT4cmCShgFKWqVwUujmg0kv0M0dZP0MZU4lK1eu/DMpKQkztuUqRoY4cszd3d1tf/3116mUwQ2WAxvMRE8nLVEYKbAQyobiKJuRKcNCNvXjjz8mbtq0KZk+94AJjuoiOtTPobt373Zbu3ath6zZGvUziz7n2RmL0egEIW/RDf+iG46S5frS0tJHS5cuPRcXF3ebiRvqKsaenp7Ov//+u4+FhcVAGYlJJ5zelTfGaMhJiBZpjKxB/dq1a3lz5849S4H8XhentcoSXUoEbKOiomZNnDjRRo7gP1OerEyuapuYD5aVkPDw8FtUqIURIZk9hBBIK/qDfqF/Mo16wgu4yRvMZC4MyRRXyXLtDz/8EL948eIz1JgCFQ/mnZpiQb/QP/RTJpAJN6aw7jr3xUydpBDr/aRd+/3338cFBgaep7fVvJ4vJnv37p3x1VdfecqAYRvhN06WKRkNGb5Ml2qLVMrV7WWxkPXr18eoeUCXOwHYv3//zHXr1k2RoUbLJhxdpU1iSiXl2bNn+8n81skSQ8ikT/QSC3nNYsLCwhb5+fmNkcH3/aCpqbm+06Qw6wbJ0mIPsiwKfkfphr120wEN3EGJiYn+MmRliLFuZC0pcgd6rLBR0XdIGiGoQ3x9fSN6MyGMBZQBB+AhjT/gyrWCyee4yX9T9eoorVL39/ePrKyszOP1CQ84AA/gwnUdcAW+cpHCbHLYIa0RBw4cSLh8+fKtHpj2dtpggAdwkSGB2iFpM4bYmPLkyZMt/fr128b1pZhcdHBwCCbGq/u4eC2+mGRmZq6RNonZ1ta2VUdHZ7tUS8E+J8oONkhJ7ToCAgJi+giR6PqrgQ9w4roOOIvbV8YXw94quphzj1NkZGTqX3/9ld4Hv2QBPsBJCimGwJvTfWGrJgWpYgpEZpK+CCuGdnZ2e8rKygr7oOeWQYMGWeXm5m7gWsEkvCsI7yGUIj8VaylUKM7lIgRCRdItIuRBd3coNjbWd+PGjfbqTApwAl5SMjEz4C7RfbW0tKzm+gJscvj2228vKSLbMjU1tdm9e/eGu3fvrv7ggw9M1DW8AC/gxnXRq7jzRVzXIENDQ875m7Nnz6aXl5eXKqI3NHo0ybR5tra2o2NiYnZQqrlgyJAhOurGCvACblzXAHfmOMjLpDQ0NCzhmnbBvqy9e/fGK7ImIWIQw5B8aL333ns+ZDW7fvnll0nYBalO1gLcgB/HNRoM/i+Tgp1+XN+MjXIpKSn3ldErWExjYyNPS0trwKeffrqipKQk6IsvvhiuLqwAN+DHdY0o/nzGCowoQxgtxXUhvVPaviwMNCpqheSYmJgMDw4O/iYtLW2lh4eHkRrw0sbgJ1GAP3O08Dkp9fX1PlxbNjGXExISkqIihRkCo9CtOTo6Trxy5coO6vAsIkqlT14BP645MeAPHl6Q0traOoPrC7HZ+uHDh1Wq1Ek23lBHdXx8fObl5+fv2Ldv3xhVJQX4AUeua1gehKTo6+tP4Lr46tWrOTwVnXRk442Ojo7x+vXrPy8uLt64fPnywSrY1A4GR4nC8oBTVpSRGVpzXXzu3LlMVXYNovHG3Nx8xJEjR/6XgusyFxeX/qrUTmk4ggfwwa+trR3FlQpjWuWPP/64z1MDQbyhQg0xR8PV1dUzOTl518mTJ7379++vqQrtA47AkysJAx98Gl2crqugoKCCOqtW+7ba29uF8YZGnd6CBQsWP3jwYNv27dudVGDQtAJPrmvAB2LKSCmklKvr3BMVnUKXRr7675s3b15HycDa+fPnmyuzTTLgOZKvra1t1VNJYeMNZTVCcoYOHepM7mx7QkLCIhsbGz1VJAV88ClrsZDmvng9QNh4QwRpTpo06QNKT3cdO3ZsSr9+/TQUTAonnuADlvI3rovy8vKqeD1IEG9gNXw+v/+yZcuWl5SUbA0MDLRT1P2l4Qk++DRS+kth9jGvhwmNRh71W/je1NR0yJ49ezZlZmZ+5u3tbawAS+HEE3yAFAOui+7evdtjSNHS0kItICTlteg6cuTY8+fP77h48aKvhYVFty0RSMMTfEjddU++uF3dySBXhQxMqHgvSTQ1NbXJWmbHxsau7K5YIwuenKRQEdamzmRgjlVPT09oHbASaVJXV9dM9cwlBweHc5ROC7qrXdJw5WwpdaifuloGYgYbN2QI/s8iIiJwYvlqVVUV9h886s72ScNVS4YOajDPPlF5IfcjJIIyGJk/k5KSkr969eoEesXWW6SrHd08YKS6Rf6TJ0+auS5wdHQ0UPXgraurK3RRBgYGMhNCqXDNxx9/fGb8+PGhRMh1+qeHPAXMhEvDE3xo0X8aKBvRl3TR8OHDB9y+fVvpTydFfIBbgsIiWJVXmpqaWkJCQq4HBQXdpLiB9Q2F9g14SiGlQUgKvZe418vOzg7be0qVQQQbF0BI555l81LWI4iOjr6NuFFcXFzAxA2Fu2UGT25SGhoaKrDHioPZt5UZsLtCyNKL1q5dmxAXF5fLe/6ki2fK6pM0PMGHVmNjI+ejKoYNGzZIXVPiysrKOkpxEw4ePJjBWLvSlyCk4Qk+tGprazkXsCwtLdWOlNbW1rbDhw/f2LBhQwrFEKS49arSNml4gg8t8q9pXBcNGTLEQo3SYgFV41mff/550r179xA3qpQRN7jSYeDJdQ344F++fPkGV8P19fX15s2bZ67qbOTk5JTNmjUr3Nvb+yQRgk3VlapECAQ4Ak+uQQU++EeOHCmtrq7mzK7mzJnjpKpk1NTUNFB6e8He3v5oTExMIgYb7/mzJVVOpOEIHsAHKvqnZWVld0xMTCRuyxk3bhy+7KIqdRAb20JDQ29RVpVcV1cHImpV3ZoZHCUKeEDXhDlnYWFhEtfFNjY2dqq04z0xMTF37Nixx/z9/f+PCMlQB0KAH3DkuoblQUhKeHj4Wa5d4Xjw2MaNG12U3bGCgoJKPz+/U5MnTw6j2iOFqTnUYl4O+HE9wA34g4cXpBw/fvwumc49pvIV+yEvLy8PZXWICqrm7777Lpaq4SMnTpzAcQzsYFerZQVp+AF/8PCCFFT3GRkZV0RYe+1DFEjfmTJlykBFdgSna0+ePPlvW1vbw5s3b/6D/h/bPpvVrW4CbsCP6xoG/yeipPCioqLCwAemNrB5+lXBrvBvvvnGS1EdSUpKyic39a9FixadqaioSON18xpHdwpwk/IgagGD/3OsRUuS/Pz85OHDhzth07S4KXCqlFvIhXxFBY4iHsyJTQwN6uamxAX43Nzc73V1dSXWJ/fv38+wtrZ2Y72A6IxfM43OKLzBlDi24rwq+OKffvrpfUWVIOpOCAR4cRHCeIUoUbf8kkkRWzZpaWk3DA0NjbCLXdyuj5aWluaRI0duoPStpzwXstvEyspKNysra4+enp7E9arGxsZaFxeX8eSlXjx06KW5cfrD/fj4+HPMPI1Ya8ENDh06NKcPcukCnLgIgQBv4C76b68uWHTs37//YFtbWwtiCjZIi5N33333/Tlz5pj1wc45pWIGnLiuAc7Am/fKMvRrq0h4NNKff/4ZwxSNYomhmKMZHBz8sZodnVaYABfgoylhvZqtBYEz82guHicpIHDLli37KdNqACnIxMTVLUOHDrXDBuk+Cl4X4AJ8uAgBvsBZXDIjdr01hSQyMhI/RilcI8dRAnHi5+e3eOHChYP6aPiPAA/gIunvqAERr4EvcBZ3jUT3QxnYSMqfL2ADNI4QwGrE1S747ZMxY8b8Q0G1i8rXJLdu3dqM32AR93d4HWyJqq6uLqZ6cDplXlli3R9HqnZ3z549BzBRhn1VsBZxbgwNOH/+/IreHl/Qf+AgiRCROUUBcAW+kr5LGpCmiYmJv7u7u09D3YIUGRvexAkFrXNeXl4RvZUUPNBn6tSpPmLnUJjTyxjcVChe9PDwWMp7vlTNk8tSWO+0bNmy72pqasrYQlJSfEGDwsLCpvZGQtBvSYSwmCE2A0fgyUWIMLuVdsO6urrS+vr6ZzNmzPCimMLHDTC3Ji7bc3R0dB4xYkR9REREYW8h5Pjx456LFy9eKunvsBBghZ/qCAwM3BYbG3uKJ2UNSJZ9n4KbN2/mDhs27G1XV9fRyBxADG4kbrOck5PTqHfeeafx1KlTBb3BQrgIQWBHtgUvQ2kylh/28mRYepAnONslJyf/PGHCBE+QgqISh3AknftAjPH29j6tLjv25Q3qly5dms/lshB/YSWIwdevX49zc3MLoH/OleX75cqYjIyMJpPV/JPSOQekyRgFIEbSRuusrKyb06dPP9ST0mWkvRcuXPgvHMfjIgQDF4QUFBRkjh079rPa2toEmUmXp0H0xUlz587dXFlZ+QAnpOC+8GQHcROXEDQ8NTX1255SYKIf6A8XIXBZePQVBisOIAEv4CbPfTpTW2hPnDhxSXR09M6BAwdasBYDkiSdDSHSnoaHh4ctX748Xh3dGdwVpk5QqZO7lngABi6ddVlEROns2bODrl27Fgqu5LlfZx4k01FSUpKTnp5e6+PjM/otEpDCTlyKizHUKU1nZ+dRK1assMsnycnJaVIXQjDbS/HjM6otvNAPrrSXjbPIWD/66KNtcXFxobxOLNS9SRVuQMFrYVRU1DaqYofCZOHGQAqsRtKSNBH4LCEh4dInn3wSrcoLZVigOnz48OzJkyd7a3KcTkJhiL6jYgch1dXVcFlbKSnC3GGnBt+bTo3o2tvbz4+JiQlC8Efj4FMRa0AM10krGllNNAIvrF69+rIqJQII5AcPHvSizHE6VeCcR+EwCNFnDEAQQoMsc+bMmTuzs7NP897g2EVXzFdpkwfzvnjx4gakyzBhtupHFYupBS7BGb+kpKQr27dvj4uPj1fajhVsA9qyZYunu7v7e1zHDUWnTdBXxFH08caNG3HTpk3bQ4X2JXljSHeQwmZxbr/99ttKf3//ZfiRTowgNF4Wq2E6Krh///5tSjeTd+/ena4I64FVbNq0aRSl7W5k6c6y/B49m+7CXYEM6lf70aNH/0Xx8lfe85/KeuPDrF09s2tHGZbfvn37VlFmNoiNM0JzohGFylaWI3PI1oqKijJp9N2JiIjIPnPmTHlXZG3IonAcYcGCBfbjx493tLS0dODKpl7KbogEkIH+sAONAnrZl19+GUKZWbishaEySIEMNDMz8z516tQKcgXvUyc0RKf92cOl8pxnRPwpLy8vJOspoeStPDc3t4oyuNq8vLzGO3fuNIkSBuBxLNrGxsZwxIgRRnZ2dqbW1tbmZBWDzc3NraTFCXFkwFUhVrLtp8ElIJcb++GHH/5WUVEBd6UWGwXhqyYEBAT8A4UmQCOrETx+/PiFUn0joERM0FWC2CToQqHBJGwj214qkoXtRX/QL/SvkyWF0sWURtY8Mu9jREo9OiXaUWhjY6MAz0EBccoWtIHIFbZJtH1kJRhU9egH+oN+qfvsBFykPfnvFWfPnj2NES2OHMpahP+maIJwL9wT90YbXiUD7UW70X70o5tcvtIEAdXF1tY24PTp0ycaGhoegRyKFwJ6/xJBLCj4G4DpSpLwXczIf8kiRN0qXBfah3aivWg3036FjWJFC57gM4JqG+etW7e6+/r6elA66oiEAMEU2Y24vQDswpro40DYDJZ9IgX7OdFXBGq8YiqIff+qYBYC2SG9CgoKCu5ERkYmbtu2LYksBz++nMNT8J5mZZoi0q+hIGjSpEmOa9asGePh4THWwsLChsDTADkAEsr90yOdSo2FREDpvaCsrCwvMTHxZnBw8K2rV6/eYYh4wFPSo+RVxT+igrYiHWZvbz9s1apVjm5ubiMorbUxNja2AEnsSGcVRLEqzqpY8F990A5IePToUSml03nJyck5ISEhd7Kzs7FKCi3kqcChJFUMWtihgfUXbNVBfWE+a9YsiwkTJgy2srJ6m8TEyMjImIo3Q9Qc7JQIyGHJQHBGbUNxo7G2traG0tjqwsLCyuvXr5dQ0C6legdnJaF4nBR+81ilFuHUIZNAgMVjenG0D49lMmRUR0Rfm1IT0UZGHzNFXt2bzk11t/y/AAMAlyq8+9fzwpgAAAAASUVORK5CYII=\n"
        //   200: invokespecial   com/flurry/sdk/aa.a:(Ljava/lang/String;)Landroid/graphics/Bitmap;
        //   203: putfield        com/flurry/sdk/aa.e:Landroid/graphics/Bitmap;
        //   206: aload_0        
        //   207: getfield        com/flurry/sdk/aa.f:Landroid/graphics/Bitmap;
        //   210: ifnonnull       232
        //   213: iconst_3       
        //   214: getstatic       com/flurry/sdk/aa.a:Ljava/lang/String;
        //   217: ldc             "Missing more info button, loading default"
        //   219: invokestatic    com/flurry/sdk/eo.a:(ILjava/lang/String;Ljava/lang/String;)V
        //   222: aload_0        
        //   223: aload_0        
        //   224: ldc             "iVBORw0KGgoAAAANSUhEUgAAAHUAAAAjCAYAAACq00VWAAAAGXRFWHRTb2Z0d2FyZQBBZG9iZSBJbWFnZVJlYWR5ccllPAAAA2hpVFh0WE1MOmNvbS5hZG9iZS54bXAAAAAAADw/eHBhY2tldCBiZWdpbj0i77u/IiBpZD0iVzVNME1wQ2VoaUh6cmVTek5UY3prYzlkIj8+IDx4OnhtcG1ldGEgeG1sbnM6eD0iYWRvYmU6bnM6bWV0YS8iIHg6eG1wdGs9IkFkb2JlIFhNUCBDb3JlIDUuMy1jMDExIDY2LjE0NTY2MSwgMjAxMi8wMi8wNi0xNDo1NjoyNyAgICAgICAgIj4gPHJkZjpSREYgeG1sbnM6cmRmPSJodHRwOi8vd3d3LnczLm9yZy8xOTk5LzAyLzIyLXJkZi1zeW50YXgtbnMjIj4gPHJkZjpEZXNjcmlwdGlvbiByZGY6YWJvdXQ9IiIgeG1sbnM6eG1wTU09Imh0dHA6Ly9ucy5hZG9iZS5jb20veGFwLzEuMC9tbS8iIHhtbG5zOnN0UmVmPSJodHRwOi8vbnMuYWRvYmUuY29tL3hhcC8xLjAvc1R5cGUvUmVzb3VyY2VSZWYjIiB4bWxuczp4bXA9Imh0dHA6Ly9ucy5hZG9iZS5jb20veGFwLzEuMC8iIHhtcE1NOk9yaWdpbmFsRG9jdW1lbnRJRD0ieG1wLmRpZDo2NTlBNDE0ODBBMjA2ODExODA4M0E0ODdERThGMTBDNCIgeG1wTU06RG9jdW1lbnRJRD0ieG1wLmRpZDo3MDRBMTNGRTkxMjQxMUUzODZEM0FGOEMyMzQ5MDcxOSIgeG1wTU06SW5zdGFuY2VJRD0ieG1wLmlpZDo3MDRBMTNGRDkxMjQxMUUzODZEM0FGOEMyMzQ5MDcxOSIgeG1wOkNyZWF0b3JUb29sPSJBZG9iZSBQaG90b3Nob3AgQ1M2IChNYWNpbnRvc2gpIj4gPHhtcE1NOkRlcml2ZWRGcm9tIHN0UmVmOmluc3RhbmNlSUQ9InhtcC5paWQ6RkM3RjExNzQwNzIwNjgxMTgyMkFENjgzNEE1MTM3ODMiIHN0UmVmOmRvY3VtZW50SUQ9InhtcC5kaWQ6NjU5QTQxNDgwQTIwNjgxMTgwODNBNDg3REU4RjEwQzQiLz4gPC9yZGY6RGVzY3JpcHRpb24+IDwvcmRmOlJERj4gPC94OnhtcG1ldGE+IDw/eHBhY2tldCBlbmQ9InIiPz4zByGOAAAFr0lEQVR42uxbW0hjRxg2cZOUGBWJiiirqxhU0NoHtQgKioiKKCi0L4qXR10IgmJEXzQgqCD0SV+9vlRQ8AKKiIqgVAWXYlCI1Y27Td14q2lMiTax8y3Ocjiek9ruanPC/DCcnDn/zJn//+a/TTiyu7u7gHt6Rdo3pEWSpghgJBW6Jc1G2hvS3qLjxf2Db3t7e78fGRn5+uDgIObm5oaBKhFSKpW3Op3ufU1Nzc+tra0TpOsngPqqr6/vO6PRWOR0OlVMTdIiGKDJZIrv6uqKJl5XZjAYPsjhcmGhDFBpE/ADjsAToEaazeYYphbpEwmd0cAToCqICSuZSvzCFQNHhZypwv+IgcpAZcRAZSQNUEktlLi8vBwpdcEHBgZCIAtaXV2d13IuNTVVfn19nQDesbGxMGapvl/feSorKzXeeBobGzVqtVrut5bqb7S5uekoKCgI9caTn5+v2dracjBQJULr6+tOWGF3d7egtRYXFyuSk5PVi4uLDFQQ4g+NRWinp6dx/JiEeIUYTXmE+Gj8g+ItFstLGttwxTNibVHc8bjHvI9Z48XFhQdWWFhYKAhqdXW15vj42LW2tuYSkxHrpe+GvNPT01rupqDr3dvbw/lsIq5ULioPbdyxPgcqFl5UVBQyPDx8JpPJDtAWFhbsFRUVYdyFE0BfJiQkqOrr699x+aqqqrQQmjtne3t71OHhoQs8Ozs7H5Xc0NAQGRwcLE9LSztEP+aJj49Xzc3NPfroE1aYmZmpEdoIubm5GgKoQ8R1R2GdWC9dO+TNzs7+uPm4vODDtaSkxJKSkmIFyFg75qZjW1parOnp6Wr+2H9NZHe8JhfzYxvhvyNAXHnjIWB8AB/ZpW+9PSOW9xt+k+zzmM9HFPYH2RjX3DHc9zY3N/+KPsrDbd7m5a8D8+CeWJibKPqMy4Px4CFg/4L14jfloePxLv7cdBx46ThizTf0Oe3DHPyx3p49Ep/XT2KppaWloXBp8/PztwKZpJ26Nbi+mZmZy6GhoQeuDdbH7yNWcMXvm5yctPP7qKvUarWBj13z0tLSFayS24eseH9/37m7u+vh82dkZKjPzs5uOzo6Hlgx5IHL5s4Ha+boIARZN9UFl6AzvBPz/1f9v3gKUGNjY1VoiBFiPDExMQoC7GV/f78Trgj36M/LywvBhiDJSyAR3M0dc3Jy4hGKiV9izWRzOMrKysJQs9JNhqwY7lSIHy7+6OjIJTYfwgRkofd2u/2TLDqdToXkzJt+sGF8LqaurKx8ijNCjZQJNuL61EgsACju0fAsKyvrBEp5zoyRWhetWWk2TNzgk2S9AM2bfiIiIiw+BSqUg+RH7HQG2S4A1ev1WpPJ5ASYfL6goKBnL7eQtNCaFdkwalgh1wuClcJaxeaC/NCD0DOz2ewKDw9XiGXo8Fyfc3IlfyrlwP0COP6ztra2ULil8/NzN3iIpXqEakNko88Nak9PzxXcIrJuvH92dlbUSre3t50ARqi+hdyQTSxrXl1d/ZPqQmgszZR9ClQoB7vUaDRGccsS7D4smCZHcNEAmM8zOjoa/X8U7bBKJCkoNeAeEe+9HB3aEfubmpoi+TU15MY8yBmExmJeyA5dcMs7jCVAR0B3YmOfDFQAwS2Y+Q1npXFxce+QUUJBtB916/j4+Hl5efn5/fGbDcJxeZAxTkxMXA4ODtpwkoOY+5zAktDg4GerYoTYPzU1dQm56Ppra2vD0Yda9B+OHm3QBWpaOhZ62NjYcEB3nyODDHUNCcxNAYz8ggieP7D/U/2QGKgMVEYMVEYMVEZfDtRbpVJ5w1QhfcLHUsAToNoSExOtTCXSJ4Ij/ka0AdQ3+AxOrVa7mFqkS8APOALPwM7Ozt9zcnKu5HL5V1arVWW32zVut5vFWum43L+SkpKO9Xr9usFg+JF0mWScL8njSUsPYF+SS40efEn+twADANDWCy3XoCV5AAAAAElFTkSuQmCC\n"
        //   226: invokespecial   com/flurry/sdk/aa.a:(Ljava/lang/String;)Landroid/graphics/Bitmap;
        //   229: putfield        com/flurry/sdk/aa.f:Landroid/graphics/Bitmap;
        //   232: aload_0        
        //   233: iconst_1       
        //   234: putfield        com/flurry/sdk/aa.b:Z
        //   237: return         
        //   238: aload           4
        //   240: invokestatic    com/flurry/sdk/fe.a:(Ljava/io/Closeable;)V
        //   243: aload_3        
        //   244: invokestatic    com/flurry/sdk/fe.a:(Ljava/io/Closeable;)V
        //   247: goto            107
        //   250: astore          16
        //   252: aconst_null    
        //   253: astore_3       
        //   254: iconst_3       
        //   255: getstatic       com/flurry/sdk/aa.a:Ljava/lang/String;
        //   258: ldc             "Error unzipping media assets file!!!"
        //   260: invokestatic    com/flurry/sdk/eo.a:(ILjava/lang/String;Ljava/lang/String;)V
        //   263: aload_1        
        //   264: invokestatic    com/flurry/sdk/fe.a:(Ljava/io/Closeable;)V
        //   267: aload_3        
        //   268: invokestatic    com/flurry/sdk/fe.a:(Ljava/io/Closeable;)V
        //   271: goto            107
        //   274: astore          6
        //   276: aconst_null    
        //   277: astore_3       
        //   278: aload_1        
        //   279: invokestatic    com/flurry/sdk/fe.a:(Ljava/io/Closeable;)V
        //   282: aload_3        
        //   283: invokestatic    com/flurry/sdk/fe.a:(Ljava/io/Closeable;)V
        //   286: aload           6
        //   288: athrow         
        //   289: astore          6
        //   291: goto            278
        //   294: astore          8
        //   296: aload           4
        //   298: astore_1       
        //   299: aload           8
        //   301: astore          6
        //   303: goto            278
        //   306: astore          11
        //   308: aload           10
        //   310: astore_3       
        //   311: aload           4
        //   313: astore_1       
        //   314: aload           11
        //   316: astore          6
        //   318: goto            278
        //   321: astore          14
        //   323: aconst_null    
        //   324: astore_1       
        //   325: goto            254
        //   328: astore          5
        //   330: aload           4
        //   332: astore_1       
        //   333: goto            254
        //   336: astore          15
        //   338: aconst_null    
        //   339: astore          4
        //   341: aconst_null    
        //   342: astore          10
        //   344: goto            88
        //   347: astore          13
        //   349: aload_3        
        //   350: astore          10
        //   352: aconst_null    
        //   353: astore          4
        //   355: goto            88
        //    Exceptions:
        //  Try           Handler
        //  Start  End    Start  End    Type                           
        //  -----  -----  -----  -----  -------------------------------
        //  24     40     336    347    Ljava/io/FileNotFoundException;
        //  24     40     250    254    Ljava/io/IOException;
        //  24     40     274    278    Any
        //  40     57     347    358    Ljava/io/FileNotFoundException;
        //  40     57     321    328    Ljava/io/IOException;
        //  40     57     289    294    Any
        //  57     64     83     88     Ljava/io/FileNotFoundException;
        //  57     64     328    336    Ljava/io/IOException;
        //  57     64     294    306    Any
        //  69     80     83     88     Ljava/io/FileNotFoundException;
        //  69     80     328    336    Ljava/io/IOException;
        //  69     80     294    306    Any
        //  88     97     306    321    Any
        //  254    263    289    294    Any
        // 
        // The error that occurred was:
        // 
        // java.lang.IllegalStateException: Expression is linked from several locations: Label_0057:
        //     at com.strobel.decompiler.ast.Error.expressionLinkedFromMultipleLocations(Error.java:27)
        //     at com.strobel.decompiler.ast.AstOptimizer.mergeDisparateObjectInitializations(AstOptimizer.java:2592)
        //     at com.strobel.decompiler.ast.AstOptimizer.optimize(AstOptimizer.java:235)
        //     at com.strobel.decompiler.ast.AstOptimizer.optimize(AstOptimizer.java:42)
        //     at com.strobel.decompiler.languages.java.ast.AstMethodBodyBuilder.createMethodBody(AstMethodBodyBuilder.java:214)
        //     at com.strobel.decompiler.languages.java.ast.AstMethodBodyBuilder.createMethodBody(AstMethodBodyBuilder.java:99)
        //     at com.strobel.decompiler.languages.java.ast.AstBuilder.createMethodBody(AstBuilder.java:757)
        //     at com.strobel.decompiler.languages.java.ast.AstBuilder.createMethod(AstBuilder.java:655)
        //     at com.strobel.decompiler.languages.java.ast.AstBuilder.addTypeMembers(AstBuilder.java:532)
        //     at com.strobel.decompiler.languages.java.ast.AstBuilder.createTypeCore(AstBuilder.java:499)
        //     at com.strobel.decompiler.languages.java.ast.AstBuilder.createTypeNoCache(AstBuilder.java:141)
        //     at com.strobel.decompiler.languages.java.ast.AstBuilder.createType(AstBuilder.java:130)
        //     at com.strobel.decompiler.languages.java.ast.AstBuilder.addType(AstBuilder.java:105)
        //     at com.strobel.decompiler.languages.java.JavaLanguage.buildAst(JavaLanguage.java:71)
        //     at com.strobel.decompiler.languages.java.JavaLanguage.decompileType(JavaLanguage.java:59)
        //     at com.strobel.decompiler.DecompilerDriver.decompileType(DecompilerDriver.java:314)
        //     at com.strobel.decompiler.DecompilerDriver.decompileJar(DecompilerDriver.java:235)
        //     at com.strobel.decompiler.DecompilerDriver.main(DecompilerDriver.java:120)
        // 
        throw new IllegalStateException("An error occurred while decompiling this method.");
    }
}
