// 
// Decompiled by Procyon v0.5.29
// 

package android.support.v4.c;

import java.lang.reflect.Array;
import java.util.Set;
import java.util.Iterator;
import java.util.Collection;
import java.util.Map;
import android.support.v4.c.f$android.support.v4.c.k;
import android.support.v4.c.f$android.support.v4.c.i;
import android.support.v4.c.f$android.support.v4.c.h;

abstract class f<K, V>
{
    h b;
    i c;
    k d;
    
    public static <K, V> boolean a(final Map<K, V> map, final Collection<?> collection) {
        final Iterator<?> iterator = collection.iterator();
        while (iterator.hasNext()) {
            if (!map.containsKey(iterator.next())) {
                return false;
            }
        }
        return true;
    }
    
    public static <T> boolean a(final Set<T> set, final Object o) {
        boolean b = true;
        boolean b2;
        if (set == o) {
            b2 = b;
        }
        else {
            final boolean b3 = o instanceof Set;
            b2 = false;
            if (b3) {
                final Set set2 = (Set)o;
                try {
                    if (set.size() != set2.size() || !set.containsAll(set2)) {
                        b = false;
                    }
                    return b;
                }
                catch (ClassCastException ex) {
                    return false;
                }
                catch (NullPointerException ex2) {
                    return false;
                }
            }
        }
        return b2;
    }
    
    public static <K, V> boolean b(final Map<K, V> map, final Collection<?> collection) {
        final int size = map.size();
        final Iterator<?> iterator = collection.iterator();
        while (iterator.hasNext()) {
            map.remove(iterator.next());
        }
        return size != map.size();
    }
    
    public static <K, V> boolean c(final Map<K, V> map, final Collection<?> collection) {
        final int size = map.size();
        final Iterator<K> iterator = map.keySet().iterator();
        while (iterator.hasNext()) {
            if (!collection.contains(iterator.next())) {
                iterator.remove();
            }
        }
        return size != map.size();
    }
    
    protected abstract int a();
    
    protected abstract int a(final Object p0);
    
    protected abstract Object a(final int p0, final int p1);
    
    protected abstract V a(final int p0, final V p1);
    
    protected abstract void a(final int p0);
    
    protected abstract void a(final K p0, final V p1);
    
    public <T> T[] a(final T[] array, final int n) {
        final int a = this.a();
        Object[] array2;
        if (array.length < a) {
            array2 = (Object[])Array.newInstance(array.getClass().getComponentType(), a);
        }
        else {
            array2 = array;
        }
        for (int i = 0; i < a; ++i) {
            array2[i] = this.a(i, n);
        }
        if (array2.length > a) {
            array2[a] = null;
        }
        return (T[])array2;
    }
    
    protected abstract int b(final Object p0);
    
    protected abstract Map<K, V> b();
    
    public Object[] b(final int n) {
        final int a = this.a();
        final Object[] array = new Object[a];
        for (int i = 0; i < a; ++i) {
            array[i] = this.a(i, n);
        }
        return array;
    }
    
    protected abstract void c();
    
    public Set<Map.Entry<K, V>> d() {
        // 
        // This method could not be decompiled.
        // 
        // Original Bytecode:
        // 
        //     0: aload_0        
        //     1: getfield        android/support/v4/c/f.b:getfield       !!! ERROR
        //     4: ifnonnull       19
        //     7: aload_0        
        //     8: new             new            !!! ERROR
        //    11: dup            
        //    12: aload_0        
        //    13: invokespecial   invokespecial  !!! ERROR
        //    16: putfield        android/support/v4/c/f.b:putfield       !!! ERROR
        //    19: aload_0        
        //    20: getfield        android/support/v4/c/f.b:getfield       !!! ERROR
        //    23: areturn        
        //    Signature:
        //  ()Ljava/util/Set<Ljava/util/Map$Entry<TK;TV;>;>;
        // 
        // The error that occurred was:
        // 
        // java.lang.IllegalArgumentException: Argument 'typeArguments' must not have any null elements.
        //     at com.strobel.core.VerifyArgument.noNullElementsAndNotEmpty(VerifyArgument.java:145)
        //     at com.strobel.assembler.metadata.CoreMetadataFactory$UnresolvedType.makeGenericType(CoreMetadataFactory.java:566)
        //     at com.strobel.assembler.metadata.CoreMetadataFactory.makeParameterizedType(CoreMetadataFactory.java:154)
        //     at com.strobel.assembler.metadata.signatures.Reifier.visitClassTypeSignature(Reifier.java:125)
        //     at com.strobel.assembler.metadata.signatures.ClassTypeSignature.accept(ClassTypeSignature.java:46)
        //     at com.strobel.assembler.metadata.signatures.Reifier.reifyTypeArguments(Reifier.java:53)
        //     at com.strobel.assembler.metadata.signatures.Reifier.visitClassTypeSignature(Reifier.java:123)
        //     at com.strobel.assembler.metadata.signatures.ClassTypeSignature.accept(ClassTypeSignature.java:46)
        //     at com.strobel.assembler.metadata.MetadataParser.parseClassSignature(MetadataParser.java:404)
        //     at com.strobel.assembler.metadata.ClassFileReader.populateBaseTypes(ClassFileReader.java:665)
        //     at com.strobel.assembler.metadata.ClassFileReader.readClass(ClassFileReader.java:438)
        //     at com.strobel.assembler.metadata.ClassFileReader.readClass(ClassFileReader.java:366)
        //     at com.strobel.assembler.metadata.MetadataSystem.resolveType(MetadataSystem.java:124)
        //     at com.strobel.decompiler.NoRetryMetadataSystem.resolveType(DecompilerDriver.java:460)
        //     at com.strobel.assembler.metadata.MetadataSystem.resolveCore(MetadataSystem.java:76)
        //     at com.strobel.assembler.metadata.MetadataResolver.resolve(MetadataResolver.java:104)
        //     at com.strobel.assembler.metadata.CoreMetadataFactory$UnresolvedType.resolve(CoreMetadataFactory.java:576)
        //     at com.strobel.assembler.metadata.MetadataResolver.resolve(MetadataResolver.java:128)
        //     at com.strobel.assembler.metadata.CoreMetadataFactory$UnresolvedType.resolve(CoreMetadataFactory.java:586)
        //     at com.strobel.assembler.metadata.MethodReference.resolve(MethodReference.java:172)
        //     at com.strobel.decompiler.ast.TypeAnalysis.inferCall(TypeAnalysis.java:2420)
        //     at com.strobel.decompiler.ast.TypeAnalysis.doInferTypeForExpression(TypeAnalysis.java:1029)
        //     at com.strobel.decompiler.ast.TypeAnalysis.inferTypeForExpression(TypeAnalysis.java:803)
        //     at com.strobel.decompiler.ast.TypeAnalysis.runInference(TypeAnalysis.java:672)
        //     at com.strobel.decompiler.ast.TypeAnalysis.runInference(TypeAnalysis.java:655)
        //     at com.strobel.decompiler.ast.TypeAnalysis.runInference(TypeAnalysis.java:365)
        //     at com.strobel.decompiler.ast.TypeAnalysis.run(TypeAnalysis.java:96)
        //     at com.strobel.decompiler.ast.AstOptimizer.optimize(AstOptimizer.java:109)
        //     at com.strobel.decompiler.ast.AstOptimizer.optimize(AstOptimizer.java:42)
        //     at com.strobel.decompiler.languages.java.ast.AstMethodBodyBuilder.createMethodBody(AstMethodBodyBuilder.java:214)
        //     at com.strobel.decompiler.languages.java.ast.AstMethodBodyBuilder.createMethodBody(AstMethodBodyBuilder.java:99)
        //     at com.strobel.decompiler.languages.java.ast.AstBuilder.createMethodBody(AstBuilder.java:757)
        //     at com.strobel.decompiler.languages.java.ast.AstBuilder.createMethod(AstBuilder.java:655)
        //     at com.strobel.decompiler.languages.java.ast.AstBuilder.addTypeMembers(AstBuilder.java:532)
        //     at com.strobel.decompiler.languages.java.ast.AstBuilder.createTypeCore(AstBuilder.java:499)
        //     at com.strobel.decompiler.languages.java.ast.AstBuilder.createTypeNoCache(AstBuilder.java:141)
        //     at com.strobel.decompiler.languages.java.ast.AstBuilder.createType(AstBuilder.java:130)
        //     at com.strobel.decompiler.languages.java.ast.AstBuilder.addType(AstBuilder.java:105)
        //     at com.strobel.decompiler.languages.java.JavaLanguage.buildAst(JavaLanguage.java:71)
        //     at com.strobel.decompiler.languages.java.JavaLanguage.decompileType(JavaLanguage.java:59)
        //     at com.strobel.decompiler.DecompilerDriver.decompileType(DecompilerDriver.java:314)
        //     at com.strobel.decompiler.DecompilerDriver.decompileJar(DecompilerDriver.java:235)
        //     at com.strobel.decompiler.DecompilerDriver.main(DecompilerDriver.java:120)
        // 
        throw new IllegalStateException("An error occurred while decompiling this method.");
    }
    
    public Set<K> e() {
        // 
        // This method could not be decompiled.
        // 
        // Original Bytecode:
        // 
        //     0: aload_0        
        //     1: getfield        android/support/v4/c/f.c:getfield       !!! ERROR
        //     4: ifnonnull       19
        //     7: aload_0        
        //     8: new             new            !!! ERROR
        //    11: dup            
        //    12: aload_0        
        //    13: invokespecial   invokespecial  !!! ERROR
        //    16: putfield        android/support/v4/c/f.c:putfield       !!! ERROR
        //    19: aload_0        
        //    20: getfield        android/support/v4/c/f.c:getfield       !!! ERROR
        //    23: areturn        
        //    Signature:
        //  ()Ljava/util/Set<TK;>;
        // 
        // The error that occurred was:
        // 
        // java.lang.IllegalArgumentException: Argument 'typeArguments' must not have any null elements.
        //     at com.strobel.core.VerifyArgument.noNullElementsAndNotEmpty(VerifyArgument.java:145)
        //     at com.strobel.assembler.metadata.CoreMetadataFactory$UnresolvedType.makeGenericType(CoreMetadataFactory.java:566)
        //     at com.strobel.assembler.metadata.CoreMetadataFactory.makeParameterizedType(CoreMetadataFactory.java:154)
        //     at com.strobel.assembler.metadata.signatures.Reifier.visitClassTypeSignature(Reifier.java:125)
        //     at com.strobel.assembler.metadata.signatures.ClassTypeSignature.accept(ClassTypeSignature.java:46)
        //     at com.strobel.assembler.metadata.MetadataParser.parseClassSignature(MetadataParser.java:404)
        //     at com.strobel.assembler.metadata.ClassFileReader.populateBaseTypes(ClassFileReader.java:665)
        //     at com.strobel.assembler.metadata.ClassFileReader.readClass(ClassFileReader.java:438)
        //     at com.strobel.assembler.metadata.ClassFileReader.readClass(ClassFileReader.java:366)
        //     at com.strobel.assembler.metadata.MetadataSystem.resolveType(MetadataSystem.java:124)
        //     at com.strobel.decompiler.NoRetryMetadataSystem.resolveType(DecompilerDriver.java:460)
        //     at com.strobel.assembler.metadata.MetadataSystem.resolveCore(MetadataSystem.java:76)
        //     at com.strobel.assembler.metadata.MetadataResolver.resolve(MetadataResolver.java:104)
        //     at com.strobel.assembler.metadata.CoreMetadataFactory$UnresolvedType.resolve(CoreMetadataFactory.java:576)
        //     at com.strobel.assembler.metadata.MetadataResolver.resolve(MetadataResolver.java:128)
        //     at com.strobel.assembler.metadata.CoreMetadataFactory$UnresolvedType.resolve(CoreMetadataFactory.java:586)
        //     at com.strobel.assembler.metadata.MethodReference.resolve(MethodReference.java:172)
        //     at com.strobel.decompiler.ast.TypeAnalysis.inferCall(TypeAnalysis.java:2420)
        //     at com.strobel.decompiler.ast.TypeAnalysis.doInferTypeForExpression(TypeAnalysis.java:1029)
        //     at com.strobel.decompiler.ast.TypeAnalysis.inferTypeForExpression(TypeAnalysis.java:803)
        //     at com.strobel.decompiler.ast.TypeAnalysis.runInference(TypeAnalysis.java:672)
        //     at com.strobel.decompiler.ast.TypeAnalysis.runInference(TypeAnalysis.java:655)
        //     at com.strobel.decompiler.ast.TypeAnalysis.runInference(TypeAnalysis.java:365)
        //     at com.strobel.decompiler.ast.TypeAnalysis.run(TypeAnalysis.java:96)
        //     at com.strobel.decompiler.ast.AstOptimizer.optimize(AstOptimizer.java:109)
        //     at com.strobel.decompiler.ast.AstOptimizer.optimize(AstOptimizer.java:42)
        //     at com.strobel.decompiler.languages.java.ast.AstMethodBodyBuilder.createMethodBody(AstMethodBodyBuilder.java:214)
        //     at com.strobel.decompiler.languages.java.ast.AstMethodBodyBuilder.createMethodBody(AstMethodBodyBuilder.java:99)
        //     at com.strobel.decompiler.languages.java.ast.AstBuilder.createMethodBody(AstBuilder.java:757)
        //     at com.strobel.decompiler.languages.java.ast.AstBuilder.createMethod(AstBuilder.java:655)
        //     at com.strobel.decompiler.languages.java.ast.AstBuilder.addTypeMembers(AstBuilder.java:532)
        //     at com.strobel.decompiler.languages.java.ast.AstBuilder.createTypeCore(AstBuilder.java:499)
        //     at com.strobel.decompiler.languages.java.ast.AstBuilder.createTypeNoCache(AstBuilder.java:141)
        //     at com.strobel.decompiler.languages.java.ast.AstBuilder.createType(AstBuilder.java:130)
        //     at com.strobel.decompiler.languages.java.ast.AstBuilder.addType(AstBuilder.java:105)
        //     at com.strobel.decompiler.languages.java.JavaLanguage.buildAst(JavaLanguage.java:71)
        //     at com.strobel.decompiler.languages.java.JavaLanguage.decompileType(JavaLanguage.java:59)
        //     at com.strobel.decompiler.DecompilerDriver.decompileType(DecompilerDriver.java:314)
        //     at com.strobel.decompiler.DecompilerDriver.decompileJar(DecompilerDriver.java:235)
        //     at com.strobel.decompiler.DecompilerDriver.main(DecompilerDriver.java:120)
        // 
        throw new IllegalStateException("An error occurred while decompiling this method.");
    }
    
    public Collection<V> f() {
        // 
        // This method could not be decompiled.
        // 
        // Original Bytecode:
        // 
        //     0: aload_0        
        //     1: getfield        android/support/v4/c/f.d:getfield       !!! ERROR
        //     4: ifnonnull       19
        //     7: aload_0        
        //     8: new             new            !!! ERROR
        //    11: dup            
        //    12: aload_0        
        //    13: invokespecial   invokespecial  !!! ERROR
        //    16: putfield        android/support/v4/c/f.d:putfield       !!! ERROR
        //    19: aload_0        
        //    20: getfield        android/support/v4/c/f.d:getfield       !!! ERROR
        //    23: areturn        
        //    Signature:
        //  ()Ljava/util/Collection<TV;>;
        // 
        // The error that occurred was:
        // 
        // java.lang.IllegalArgumentException: Argument 'typeArguments' must not have any null elements.
        //     at com.strobel.core.VerifyArgument.noNullElementsAndNotEmpty(VerifyArgument.java:145)
        //     at com.strobel.assembler.metadata.CoreMetadataFactory$UnresolvedType.makeGenericType(CoreMetadataFactory.java:566)
        //     at com.strobel.assembler.metadata.CoreMetadataFactory.makeParameterizedType(CoreMetadataFactory.java:154)
        //     at com.strobel.assembler.metadata.signatures.Reifier.visitClassTypeSignature(Reifier.java:125)
        //     at com.strobel.assembler.metadata.signatures.ClassTypeSignature.accept(ClassTypeSignature.java:46)
        //     at com.strobel.assembler.metadata.MetadataParser.parseClassSignature(MetadataParser.java:404)
        //     at com.strobel.assembler.metadata.ClassFileReader.populateBaseTypes(ClassFileReader.java:665)
        //     at com.strobel.assembler.metadata.ClassFileReader.readClass(ClassFileReader.java:438)
        //     at com.strobel.assembler.metadata.ClassFileReader.readClass(ClassFileReader.java:366)
        //     at com.strobel.assembler.metadata.MetadataSystem.resolveType(MetadataSystem.java:124)
        //     at com.strobel.decompiler.NoRetryMetadataSystem.resolveType(DecompilerDriver.java:460)
        //     at com.strobel.assembler.metadata.MetadataSystem.resolveCore(MetadataSystem.java:76)
        //     at com.strobel.assembler.metadata.MetadataResolver.resolve(MetadataResolver.java:104)
        //     at com.strobel.assembler.metadata.CoreMetadataFactory$UnresolvedType.resolve(CoreMetadataFactory.java:576)
        //     at com.strobel.assembler.metadata.MetadataResolver.resolve(MetadataResolver.java:128)
        //     at com.strobel.assembler.metadata.CoreMetadataFactory$UnresolvedType.resolve(CoreMetadataFactory.java:586)
        //     at com.strobel.assembler.metadata.MethodReference.resolve(MethodReference.java:172)
        //     at com.strobel.decompiler.ast.TypeAnalysis.inferCall(TypeAnalysis.java:2420)
        //     at com.strobel.decompiler.ast.TypeAnalysis.doInferTypeForExpression(TypeAnalysis.java:1029)
        //     at com.strobel.decompiler.ast.TypeAnalysis.inferTypeForExpression(TypeAnalysis.java:803)
        //     at com.strobel.decompiler.ast.TypeAnalysis.runInference(TypeAnalysis.java:672)
        //     at com.strobel.decompiler.ast.TypeAnalysis.runInference(TypeAnalysis.java:655)
        //     at com.strobel.decompiler.ast.TypeAnalysis.runInference(TypeAnalysis.java:365)
        //     at com.strobel.decompiler.ast.TypeAnalysis.run(TypeAnalysis.java:96)
        //     at com.strobel.decompiler.ast.AstOptimizer.optimize(AstOptimizer.java:109)
        //     at com.strobel.decompiler.ast.AstOptimizer.optimize(AstOptimizer.java:42)
        //     at com.strobel.decompiler.languages.java.ast.AstMethodBodyBuilder.createMethodBody(AstMethodBodyBuilder.java:214)
        //     at com.strobel.decompiler.languages.java.ast.AstMethodBodyBuilder.createMethodBody(AstMethodBodyBuilder.java:99)
        //     at com.strobel.decompiler.languages.java.ast.AstBuilder.createMethodBody(AstBuilder.java:757)
        //     at com.strobel.decompiler.languages.java.ast.AstBuilder.createMethod(AstBuilder.java:655)
        //     at com.strobel.decompiler.languages.java.ast.AstBuilder.addTypeMembers(AstBuilder.java:532)
        //     at com.strobel.decompiler.languages.java.ast.AstBuilder.createTypeCore(AstBuilder.java:499)
        //     at com.strobel.decompiler.languages.java.ast.AstBuilder.createTypeNoCache(AstBuilder.java:141)
        //     at com.strobel.decompiler.languages.java.ast.AstBuilder.createType(AstBuilder.java:130)
        //     at com.strobel.decompiler.languages.java.ast.AstBuilder.addType(AstBuilder.java:105)
        //     at com.strobel.decompiler.languages.java.JavaLanguage.buildAst(JavaLanguage.java:71)
        //     at com.strobel.decompiler.languages.java.JavaLanguage.decompileType(JavaLanguage.java:59)
        //     at com.strobel.decompiler.DecompilerDriver.decompileType(DecompilerDriver.java:314)
        //     at com.strobel.decompiler.DecompilerDriver.decompileJar(DecompilerDriver.java:235)
        //     at com.strobel.decompiler.DecompilerDriver.main(DecompilerDriver.java:120)
        // 
        throw new IllegalStateException("An error occurred while decompiling this method.");
    }
}
